morel/__init__.py
morel/app.py
morel/exploit_template.py
morel/exploits.py
morel/logger.py
morel/singleton.py
morel/target.py
morel/target_template.py
morel-1.6.4.dist-info/LICENSE
morel-1.6.4.dist-info/METADATA
morel-1.6.4.dist-info/WHEEL
morel-1.6.4.dist-info/entry_points.txt
morel-1.6.4.dist-info/top_level.txt
morel-1.6.4.dist-info/RECORD
